mcp_ephemeral_k8s/__init__.py
mcp_ephemeral_k8s/cli.py
mcp_ephemeral_k8s/session_manager.py
mcp_ephemeral_k8s/api/__init__.py
mcp_ephemeral_k8s/api/ephemeral_mcp_server.py
mcp_ephemeral_k8s/api/exceptions.py
mcp_ephemeral_k8s/app/__init__.py
mcp_ephemeral_k8s/app/mcp_server.py
mcp_ephemeral_k8s/integrations/__init__.py
mcp_ephemeral_k8s/integrations/presets.py
mcp_ephemeral_k8s/k8s/__init__.py
mcp_ephemeral_k8s/k8s/job.py
mcp_ephemeral_k8s/k8s/rbac.py
mcp_ephemeral_k8s/k8s/uid.py
mcp_ephemeral_k8s-0.0.4.dist-info/METADATA
mcp_ephemeral_k8s-0.0.4.dist-info/WHEEL
mcp_ephemeral_k8s-0.0.4.dist-info/entry_points.txt
mcp_ephemeral_k8s-0.0.4.dist-info/licenses/LICENSE
mcp_ephemeral_k8s-0.0.4.dist-info/RECORD
