Metadata-Version: 2.4
Name: mcp-ephemeral-k8s
Version: 0.0.4
Summary: Python implementation to spawn ephemeral Model Context Protocol (MCP) servers using the kubernetes API.
Project-URL: Homepage, https://BobMerkus.github.io/mcp-ephemeral-k8s/
Project-URL: Repository, https://github.com/BobMerkus/mcp-ephemeral-k8s
Project-URL: Documentation, https://BobMerkus.github.io/mcp-ephemeral-k8s/
Author-email: Bob Merkus <bob.merkus@gmail.com>
License-File: LICENSE
Keywords: python
Classifier: Intended Audience :: Developers
Classifier: Programming Language :: Python
Classifier: Programming Language :: Python :: 3
Classifier: Programming Language :: Python :: 3.11
Classifier: Programming Language :: Python :: 3.12
Classifier: Programming Language :: Python :: 3.13
Classifier: Topic :: Software Development :: Libraries :: Python Modules
Requires-Python: <4.0,>=3.11
Requires-Dist: fastmcp>=2.2.7
Requires-Dist: kubernetes>=32.0.1
Requires-Dist: pydantic-settings>=2.11.0
Requires-Dist: pydantic>=2.11.4
Requires-Dist: starlette>=0.49.1
